gemini_mcp/__init__.py
gemini_mcp/__main__.py
gemini_mcp/gemini_integration.py
gemini_mcp/server.py
gemini_mcp_server-0.0.1.dist-info/METADATA
gemini_mcp_server-0.0.1.dist-info/WHEEL
gemini_mcp_server-0.0.1.dist-info/entry_points.txt
gemini_mcp_server-0.0.1.dist-info/licenses/LICENSE
gemini_mcp_server-0.0.1.dist-info/RECORD
