Metadata-Version: 2.4
Name: gemini-mcp-server
Version: 0.0.1
Summary: MCP Server with Google Gemini CLI integration for AI second opinions
Project-URL: Homepage, https://github.com/taehun-kmu/gemini-mcp-server
Project-URL: Documentation, https://github.com/taehun-kmu/gemini-mcp-server#readme
Project-URL: Repository, https://github.com/taehun-kmu/gemini-mcp-server.git
Project-URL: Issues, https://github.com/taehun-kmu/gemini-mcp-server/issues
Author-email: taehun-kmu <taehun-kmu@kookmin.ac.kr>
License: MIT
License-File: LICENSE
Keywords: ai,development-tools,gemini,mcp,second-opinion
Classifier: Development Status :: 4 - Beta
Classifier: Intended Audience :: Developers
Classifier: License :: OSI Approved :: MIT License
Classifier: Programming Language :: Python :: 3
Classifier: Programming Language :: Python :: 3.8
Classifier: Programming Language :: Python :: 3.9
Classifier: Programming Language :: Python :: 3.10
Classifier: Programming Language :: Python :: 3.11
Classifier: Programming Language :: Python :: 3.12
Classifier: Topic :: Software Development :: Libraries :: Python Modules
Classifier: Topic :: Software Development :: Quality Assurance
Requires-Python: >=3.8
Requires-Dist: mcp>=0.1.0
Requires-Dist: pydantic>=2.0.0
Provides-Extra: dev
Requires-Dist: black>=23.0.0; extra == 'dev'
Requires-Dist: mypy>=1.0.0; extra == 'dev'
Requires-Dist: pytest-asyncio>=0.21.0; extra == 'dev'
Requires-Dist: pytest>=7.0.0; extra == 'dev'
Requires-Dist: ruff>=0.1.0; extra == 'dev'
